{
    "class": "l-layer",
    "overlay": "-overlay",
    "header": "__header",
    "title": "__title",
    "titleIcon": "__title-icon",
    "icon": "__icon",
    "close": "close",
    "closeButton": "__close-button",
    "closeIcon": "__close-icon",
    "body": "__body",
    "layout": "__layout",
    "thumb": "-thumb",
    "footer": "__footer",
    "secondButton": "__second-button",
    "isClass": {
        "visible": "is-visible",
        "hiding": "is-hiding",
        "hidden": "is-hidden",
        "showing": "is-showing",
        "focusable": "is-focusable"
    }
}
